{
  "strategy": "主板双高猎手 T2 V1 - 每日Top1版",
  "date": "2026-06-04",
  "generated_at": "2026-06-07T20:50:38.705579+08:00",
  "source": "AkShare stock_zh_a_daily",
  "fetched_today": true,
  "alpha": 16.0,
  "top_n": 10,
  "universe": "A股主板 00/60，剔除 ST/退，停牌/零成交过滤",
  "trade_rule": "T日收盘打分；次日开盘按Top10顺序检查，若涨停无法买入则顺位递补；目标T+2收盘卖出，跌停顺延。",
  "note": "收盘后无法提前知道次日开盘是否涨停，因此这里展示的是候选Top10，不是最终成交确认。",
  "items": [
    {
      "rank": 1,
      "code": "600976",
      "name": "健民集团",
      "score": 0.1832,
      "pred_win": 0.184174,
      "pred_ret": -6.1e-05,
      "close": 90.575,
      "amount": 45099000.0,
      "turnover": 0.010608,
      "daily_return": -0.01216,
      "next_1d_date": null,
      "next_1d_return": null
    },
    {
      "rank": 2,
      "code": "601868",
      "name": "中国能建",
      "score": 0.104225,
      "pred_win": 0.164115,
      "pred_ret": -0.003743,
      "close": 2.9375,
      "amount": 1409261524.0,
      "turnover": 0.015443,
      "daily_return": -0.017544,
      "next_1d_date": null,
      "next_1d_return": null
    },
    {
      "rank": 3,
      "code": "002166",
      "name": "莱茵生物",
      "score": 0.083755,
      "pred_win": 0.16642,
      "pred_ret": -0.005167,
      "close": 59.2459,
      "amount": 61561245.0,
      "turnover": 0.010812,
      "daily_return": -0.019108,
      "next_1d_date": null,
      "next_1d_return": null
    },
    {
      "rank": 4,
      "code": "002006",
      "name": "精工科技",
      "score": 0.081995,
      "pred_win": 0.18365,
      "pred_ret": -0.006353,
      "close": 127.3164,
      "amount": 142571133.0,
      "turnover": 0.017103,
      "daily_return": 0.006931,
      "next_1d_date": null,
      "next_1d_return": null
    },
    {
      "rank": 5,
      "code": "601658",
      "name": "邮储银行",
      "score": 0.080444,
      "pred_win": 0.136041,
      "pred_ret": -0.003475,
      "close": 6.7119,
      "amount": 503959823.0,
      "turnover": 0.001405,
      "daily_return": -0.01004,
      "next_1d_date": null,
      "next_1d_return": null
    },
    {
      "rank": 6,
      "code": "601988",
      "name": "中国银行",
      "score": 0.074184,
      "pred_win": 0.144401,
      "pred_ret": -0.004389,
      "close": 15.2805,
      "amount": 1134051295.0,
      "turnover": 0.000907,
      "daily_return": -0.008403,
      "next_1d_date": null,
      "next_1d_return": null
    },
    {
      "rank": 7,
      "code": "601166",
      "name": "兴业银行",
      "score": 0.074167,
      "pred_win": 0.150013,
      "pred_ret": -0.00474,
      "close": 106.6537,
      "amount": 1417890189.0,
      "turnover": 0.003641,
      "daily_return": -0.010817,
      "next_1d_date": null,
      "next_1d_return": null
    },
    {
      "rank": 8,
      "code": "601398",
      "name": "工商银行",
      "score": 0.070252,
      "pred_win": 0.14229,
      "pred_ret": -0.004502,
      "close": 18.5616,
      "amount": 1511735233.0,
      "turnover": 0.000771,
      "daily_return": -0.006868,
      "next_1d_date": null,
      "next_1d_return": null
    },
    {
      "rank": 9,
      "code": "601916",
      "name": "浙商银行",
      "score": 0.06842,
      "pred_win": 0.13816,
      "pred_ret": -0.004359,
      "close": 4.23,
      "amount": 409868305.0,
      "turnover": 0.006206,
      "daily_return": 0.0,
      "next_1d_date": null,
      "next_1d_return": null
    },
    {
      "rank": 10,
      "code": "600036",
      "name": "招商银行",
      "score": 0.067253,
      "pred_win": 0.139573,
      "pred_ret": -0.00452,
      "close": 250.0152,
      "amount": 2826182655.0,
      "turnover": 0.003582,
      "daily_return": -0.01039,
      "next_1d_date": null,
      "next_1d_return": null
    }
  ]
}